{"metadata": {"dbt_schema_version": "https://schemas.getdbt.com/dbt/run-results/v6.json", "dbt_version": "1.11.2", "generated_at": "2026-01-10T21:07:58.622249Z", "invocation_id": "7ab76c20-9169-47ad-806c-e257f7d3629f", "invocation_started_at": "2026-01-10T21:07:56.382642Z", "env": {}}, "results": [{"status": "success", "timing": [{"name": "compile", "started_at": "2026-01-10T21:07:58.197440Z", "completed_at": "2026-01-10T21:07:58.204582Z"}, {"name": "execute", "started_at": "2026-01-10T21:07:58.204988Z", "completed_at": "2026-01-10T21:07:58.327315Z"}], "thread_id": "Thread-1 (worker)", "execution_time": 0.13136839866638184, "adapter_response": {"_message": "INSERT 0 1051", "code": "INSERT", "rows_affected": 1051}, "message": "INSERT 0 1051", "failures": null, "unique_id": "model.machine_dbt.silver_machine_events", "compiled": true, "compiled_code": "\n\nwith raw as (\n    select\n        id,\n        ts,\n        machine_id,\n        temperature::int    as temperature,\n        pressure::int       as pressure,\n        rpm::int            as rpm,\n        fault_code::int     as fault_code\n    from \"machines\".\"public\".\"bronze_machine_events\"\n),\n\n\nenriched as (\n    select\n        md5(id::text) as event_natural_key,\n        ts,\n        machine_id,\n        temperature,\n        pressure,\n        rpm,\n        fault_code\n    from raw\n)\n\nselect *\nfrom enriched\n\n\nwhere ts > (select coalesce(max(ts), '1900-01-01') from \"machines\".\"analytics\".\"silver_machine_events\")\n", "relation_name": "\"machines\".\"analytics\".\"silver_machine_events\"", "batch_results": null}, {"status": "pass", "timing": [{"name": "compile", "started_at": "2026-01-10T21:07:58.344063Z", "completed_at": "2026-01-10T21:07:58.357749Z"}, {"name": "execute", "started_at": "2026-01-10T21:07:58.358152Z", "completed_at": "2026-01-10T21:07:58.386562Z"}], "thread_id": "Thread-3 (worker)", "execution_time": 0.05234193801879883, "adapter_response": {"_message": "SELECT 1", "code": "SELECT", "rows_affected": 1}, "message": null, "failures": 0, "unique_id": "test.machine_dbt.not_null_silver_machine_events_machine_id.e2585bcea6", "compiled": true, "compiled_code": "\n    \n    \n\n\n\nselect machine_id\nfrom \"machines\".\"analytics\".\"silver_machine_events\"\nwhere machine_id is null\n\n\n", "relation_name": null, "batch_results": null}, {"status": "pass", "timing": [{"name": "compile", "started_at": "2026-01-10T21:07:58.351596Z", "completed_at": "2026-01-10T21:07:58.371045Z"}, {"name": "execute", "started_at": "2026-01-10T21:07:58.373187Z", "completed_at": "2026-01-10T21:07:58.389403Z"}], "thread_id": "Thread-2 (worker)", "execution_time": 0.055142879486083984, "adapter_response": {"_message": "SELECT 1", "code": "SELECT", "rows_affected": 1}, "message": null, "failures": 0, "unique_id": "test.machine_dbt.not_null_silver_machine_events_event_natural_key.bc6da7c0b7", "compiled": true, "compiled_code": "\n    \n    \n\n\n\nselect event_natural_key\nfrom \"machines\".\"analytics\".\"silver_machine_events\"\nwhere event_natural_key is null\n\n\n", "relation_name": null, "batch_results": null}, {"status": "pass", "timing": [{"name": "compile", "started_at": "2026-01-10T21:07:58.338699Z", "completed_at": "2026-01-10T21:07:58.368573Z"}, {"name": "execute", "started_at": "2026-01-10T21:07:58.369025Z", "completed_at": "2026-01-10T21:07:58.391170Z"}], "thread_id": "Thread-1 (worker)", "execution_time": 0.0583498477935791, "adapter_response": {"_message": "SELECT 1", "code": "SELECT", "rows_affected": 1}, "message": null, "failures": 0, "unique_id": "test.machine_dbt.unique_silver_machine_events_event_natural_key.5d7a803487", "compiled": true, "compiled_code": "\n    \n    \n\nselect\n    event_natural_key as unique_field,\n    count(*) as n_records\n\nfrom \"machines\".\"analytics\".\"silver_machine_events\"\nwhere event_natural_key is not null\ngroup by event_natural_key\nhaving count(*) > 1\n\n\n", "relation_name": null, "batch_results": null}, {"status": "pass", "timing": [{"name": "compile", "started_at": "2026-01-10T21:07:58.348923Z", "completed_at": "2026-01-10T21:07:58.370584Z"}, {"name": "execute", "started_at": "2026-01-10T21:07:58.371466Z", "completed_at": "2026-01-10T21:07:58.398478Z"}], "thread_id": "Thread-4 (worker)", "execution_time": 0.06353282928466797, "adapter_response": {"_message": "SELECT 1", "code": "SELECT", "rows_affected": 1}, "message": null, "failures": 0, "unique_id": "test.machine_dbt.not_null_silver_machine_events_ts.44d3bdc3b9", "compiled": true, "compiled_code": "\n    \n    \n\n\n\nselect ts\nfrom \"machines\".\"analytics\".\"silver_machine_events\"\nwhere ts is null\n\n\n", "relation_name": null, "batch_results": null}, {"status": "success", "timing": [{"name": "compile", "started_at": "2026-01-10T21:07:58.470479Z", "completed_at": "2026-01-10T21:07:58.472865Z"}, {"name": "execute", "started_at": "2026-01-10T21:07:58.473199Z", "completed_at": "2026-01-10T21:07:58.540506Z"}], "thread_id": "Thread-3 (worker)", "execution_time": 0.07129502296447754, "adapter_response": {"_message": "SELECT 3", "code": "SELECT", "rows_affected": 3}, "message": "SELECT 3", "failures": null, "unique_id": "model.machine_dbt.machine_hourly_stats", "compiled": true, "compiled_code": "\n\nselect\n    machine_id,\n    date_trunc('hour', ts) as hour,\n    avg(temperature) as avg_temperature,\n    avg(pressure)    as avg_pressure,\n    avg(rpm)         as avg_rpm,\n    sum(case when fault_code != 0 then 1 else 0 end) as fault_count\nfrom \"machines\".\"analytics\".\"silver_machine_events\"\ngroup by 1, 2", "relation_name": "\"machines\".\"analytics\".\"machine_hourly_stats\"", "batch_results": null}, {"status": "pass", "timing": [{"name": "compile", "started_at": "2026-01-10T21:07:58.546850Z", "completed_at": "2026-01-10T21:07:58.555698Z"}, {"name": "execute", "started_at": "2026-01-10T21:07:58.556233Z", "completed_at": "2026-01-10T21:07:58.571708Z"}], "thread_id": "Thread-1 (worker)", "execution_time": 0.029272079467773438, "adapter_response": {"_message": "SELECT 1", "code": "SELECT", "rows_affected": 1}, "message": null, "failures": 0, "unique_id": "test.machine_dbt.not_null_machine_hourly_stats_machine_id.d58363a769", "compiled": true, "compiled_code": "\n    \n    \n\n\n\nselect machine_id\nfrom \"machines\".\"analytics\".\"machine_hourly_stats\"\nwhere machine_id is null\n\n\n", "relation_name": null, "batch_results": null}, {"status": "pass", "timing": [{"name": "compile", "started_at": "2026-01-10T21:07:58.550061Z", "completed_at": "2026-01-10T21:07:58.553755Z"}, {"name": "execute", "started_at": "2026-01-10T21:07:58.554165Z", "completed_at": "2026-01-10T21:07:58.572765Z"}], "thread_id": "Thread-2 (worker)", "execution_time": 0.02937936782836914, "adapter_response": {"_message": "SELECT 1", "code": "SELECT", "rows_affected": 1}, "message": null, "failures": 0, "unique_id": "test.machine_dbt.not_null_machine_hourly_stats_hour.37e9a26b10", "compiled": true, "compiled_code": "\n    \n    \n\n\n\nselect hour\nfrom \"machines\".\"analytics\".\"machine_hourly_stats\"\nwhere hour is null\n\n\n", "relation_name": null, "batch_results": null}], "elapsed_time": 0.6621196269989014, "args": {"log_level_file": "debug", "defer": false, "require_resource_names_without_spaces": true, "require_unique_project_resource_names": false, "use_colors": true, "require_explicit_package_overrides_for_builtin_materializations": true, "use_fast_test_edges": false, "log_level": "info", "validate_macro_args": false, "select": ["silver_machine_events", "machine_hourly_stats", "fqn:*"], "macro_debugging": false, "resource_types": [], "populate_cache": true, "log_path": "C:\\Users\\matth\\Projects\\K8_God\\machine-data-platform\\dbt\\target\\dbt_models-7dae929-31136ca", "include_saved_query": false, "exclude": [], "which": "build", "log_file_max_bytes": 10485760, "exclude_resource_types": [], "printer_width": 80, "source_freshness_run_project_hooks": true, "require_nested_cumulative_type_params": false, "require_yaml_configuration_for_mf_time_spines": false, "static_parser": true, "state_modified_compare_vars": false, "log_format": "json", "empty": false, "profiles_dir": "C:\\Users\\matth\\.dbt", "upload_to_artifacts_ingest_api": false, "partial_parse_file_diff": true, "write_json": true, "export_saved_queries": false, "vars": {}, "indirect_selection": "eager", "target_path": "target\\dbt_models-7dae929-31136ca", "project_dir": "C:\\Users\\matth\\Projects\\K8_God\\machine-data-platform\\dbt", "cache_selected_only": false, "require_ref_searches_node_package_before_root": false, "favor_state": false, "strict_mode": false, "use_colors_file": true, "quiet": false, "require_batched_execution_for_custom_microbatch_strategy": false, "invocation_command": "dbt build --select silver_machine_events machine_hourly_stats --select fqn:*", "state_modified_compare_more_unrendered_values": false, "require_all_warnings_handled_by_warn_error": false, "version_check": true, "send_anonymous_usage_stats": false, "show_resource_report": false, "log_format_file": "json", "show": false, "skip_nodes_if_on_run_start_fails": false, "require_generic_test_arguments_property": true, "print": true, "warn_error_options": {"error": [], "warn": [], "silence": []}, "introspect": true, "show_all_deprecations": false, "partial_parse": true}}